image_pdf_tools/__init__.py
image_pdf_tools/utils.py
image_pdf_tools-0.3.dist-info/LICENSE
image_pdf_tools-0.3.dist-info/METADATA
image_pdf_tools-0.3.dist-info/WHEEL
image_pdf_tools-0.3.dist-info/top_level.txt
image_pdf_tools-0.3.dist-info/RECORD
