Metadata-Version: 2.1
Name: image-pdf-tools
Version: 0.3
Summary: Convert an image to pdf tools.
Home-page: https://github.com/hadpro24/image-pdf-tools
Author: Harouna Diallo
Author-email: dev.harouna@gmail.com
License: BSD-3-Clause
Platform: UNKNOWN
Classifier: Environment :: Console
Classifier: Intended Audience :: Developers
Classifier: License :: OSI Approved :: BSD License
Classifier: Operating System :: OS Independent
Classifier: Programming Language :: Python :: 3
Classifier: Programming Language :: Python :: 3 :: Only
Classifier: Programming Language :: Python :: 3.6
Classifier: Programming Language :: Python :: 3.7
Classifier: Programming Language :: Python :: 3.8
